pydozer_log-0.3.0.dist-info/METADATA
pydozer_log-0.3.0.dist-info/WHEEL
pydozer_log/__init__.py
pydozer_log/pydozer_log.cpython-38-aarch64-linux-gnu.so
pydozer_log-0.3.0.dist-info/RECORD
